hepdata_converter_ws/__init__.py
hepdata_converter_ws/__main__.py
hepdata_converter_ws/api.py
hepdata_converter_ws/version.py
hepdata_converter_ws-0.3.2.dist-info/licenses/LICENSE.txt
hepdata_converter_ws-0.3.2.dist-info/METADATA
hepdata_converter_ws-0.3.2.dist-info/WHEEL
hepdata_converter_ws-0.3.2.dist-info/entry_points.txt
hepdata_converter_ws-0.3.2.dist-info/top_level.txt
hepdata_converter_ws-0.3.2.dist-info/RECORD
