Metadata-Version: 2.4
Name: hepdata-converter-ws
Version: 0.3.2
Summary: Flask webservices enabling usage of hepdata-converter as a separate server over the network
Home-page: https://github.com/HEPData/hepdata-converter-ws
Download-URL: https://github.com/HEPData/hepdata-converter-ws/tarball/0.3.2
Author: HEPData Team
Author-email: info@hepdata.net
License: GPL
Requires-Python: >=3.7
License-File: LICENSE.txt
Requires-Dist: hepdata-converter>=0.3.3
Requires-Dist: flask
Requires-Dist: sentry-sdk[flask]
Provides-Extra: tests
Requires-Dist: coverage; extra == "tests"
Dynamic: author
Dynamic: author-email
Dynamic: description
Dynamic: description-content-type
Dynamic: download-url
Dynamic: home-page
Dynamic: license
Dynamic: license-file
Dynamic: provides-extra
Dynamic: requires-dist
Dynamic: requires-python
Dynamic: summary
